dataclass_type_validator/__init__.py
dataclass_type_validator-0.1.2.dist-info/LICENSE
dataclass_type_validator-0.1.2.dist-info/METADATA
dataclass_type_validator-0.1.2.dist-info/WHEEL
dataclass_type_validator-0.1.2.dist-info/top_level.txt
dataclass_type_validator-0.1.2.dist-info/RECORD
