Metadata-Version: 2.1
Name: dataclass-type-validator
Version: 0.1.2
Summary: Dataclass Type Validator Library
Home-page: https://github.com/levii/dataclass-type-validator
Author: Levii, inc
Author-email: contact+oss@levii.co.jp
License: UNKNOWN
Platform: UNKNOWN
Classifier: Programming Language :: Python :: 3
Classifier: License :: OSI Approved :: MIT License
Classifier: Operating System :: OS Independent
Requires-Python: >=3.8
